refyre/Refyre.py
refyre/__init__.py
refyre/ai/__init__.py
refyre/ai/question.py
refyre/cli.py
refyre/cluster/Association.py
refyre/cluster/Broadcast.py
refyre/cluster/Cache.py
refyre/cluster/Cluster.py
refyre/cluster/ClusterIterator.py
refyre/cluster/__init__.py
refyre/cluster/cogs/VariableAction.py
refyre/cluster/cogs/VariableParser.py
refyre/config/__init__.py
refyre/config/envconfig.py
refyre/config/log.py
refyre/core/AliasManager.py
refyre/core/CodeManager.py
refyre/core/RecipePreprocessor.py
refyre/core/__init__.py
refyre/datastack/DataStack.py
refyre/datastack/TorchStack.py
refyre/datastack/__init__.py
refyre/graph/FileGraph.py
refyre/graph/FileGraphNode.py
refyre/graph/__init__.py
refyre/reader/ExpressionGenerator.py
refyre/reader/Lexer.py
refyre/reader/Parser.py
refyre/reader/PatternGenerator.py
refyre/reader/__init__.py
refyre/reader/cogs/LexerToken.py
refyre/reader/cogs/lexer_utils.py
refyre/utils/__init__.py
refyre/utils/clone.py
refyre/utils/optional_imports.py
refyre/utils/regex.py
refyre-0.0.1.5.9.dist-info/METADATA
refyre-0.0.1.5.9.dist-info/WHEEL
refyre-0.0.1.5.9.dist-info/entry_points.txt
refyre-0.0.1.5.9.dist-info/RECORD
