Metadata-Version: 2.1
Name: refyre
Version: 0.0.1.5.9
Summary: Filesystem dominance is all you need.
Home-page: https://github.com/flockfysh/refyre
License: MIT
Keywords: files,manipulation,data science
Author: Ansh
Author-email: eye.am.ansh@gmail.com
Requires-Python: >=3.8
Classifier: License :: OSI Approved :: MIT License
Classifier: Operating System :: OS Independent
Classifier: Programming Language :: Python :: 3
Classifier: Programming Language :: Python :: 3.8
Classifier: Programming Language :: Python :: 3.9
Classifier: Programming Language :: Python :: 3.10
Classifier: Programming Language :: Python :: 3.11
Classifier: Programming Language :: Python :: 3.12
Provides-Extra: git
Provides-Extra: pandas
Provides-Extra: web
Requires-Dist: gitpython (>=3.1.30) ; extra == "git"
Requires-Dist: pandas (>=2.0.0) ; extra == "pandas"
Requires-Dist: requests (>=2.29.0) ; extra == "web"
Project-URL: Repository, https://github.com/flockfysh/refyre
